simpcamcap/__init__.py
simpcamcap/__main__.py
simpcamcap/simple_camera_capture.py
simpcamcap-1.0.0.dist-info/LICENSE
simpcamcap-1.0.0.dist-info/METADATA
simpcamcap-1.0.0.dist-info/WHEEL
simpcamcap-1.0.0.dist-info/entry_points.txt
simpcamcap-1.0.0.dist-info/top_level.txt
simpcamcap-1.0.0.dist-info/RECORD
