Metadata-Version: 2.1
Name: simpcamcap
Version: 1.0.0
Summary: Very simple recording tool using only OpenCV. Automatically record the camera capture to mp4, press C key or left mouse button click captures the image.
Home-page: https://github.com/PINTO0309/simpcamcap
Author: Katsuya Hyodo
Author-email: rmsdh122@yahoo.co.jp
License: MIT License
Platform: linux
Platform: unix
Requires-Python: >=3.8
License-File: LICENSE
